{
  "id": "992805cc-eb6e-440e-a8de-bb9b4692ba18",
  "prevId": "00000000-0000-0000-0000-000000000000",
  "version": "7",
  "dialect": "postgresql",
  "tables": {
    "public.close_process_on_button": {
      "name": "close_process_on_button",
      "schema": "",
      "columns": {
        "panel_id": {
          "name": "panel_id",
          "type": "varchar(19)",
          "primaryKey": false,
          "notNull": false
        },
        "trigger_custom_id": {
          "name": "trigger_custom_id",
          "type": "varchar(100)",
          "primaryKey": true,
          "notNull": true
        },
        "process": {
          "name": "process",
          "type": "jsonb[]",
          "primaryKey": false,
          "notNull": true
        },
        "created_at": {
          "name": "created_at",
          "type": "timestamp with time zone",
          "primaryKey": false,
          "notNull": true,
          "default": "now()"
        },
        "updated_at": {
          "name": "updated_at",
          "type": "timestamp with time zone",
          "primaryKey": false,
          "notNull": true,
          "default": "now()"
        }
      },
      "indexes": {
        "close_process_panel_idx": {
          "name": "close_process_panel_idx",
          "columns": [
            {
              "expression": "panel_id",
              "isExpression": false,
              "asc": true,
              "nulls": "last"
            }
          ],
          "isUnique": false,
          "concurrently": false,
          "method": "btree",
          "with": {}
        }
      },
      "foreignKeys": {},
      "compositePrimaryKeys": {},
      "uniqueConstraints": {},
      "policies": {},
      "checkConstraints": {},
      "isRLSEnabled": false
    },
    "public.ticket": {
      "name": "ticket",
      "schema": "",
      "columns": {
        "panel_id": {
          "name": "panel_id",
          "type": "varchar(19)",
          "primaryKey": true,
          "notNull": true
        },
        "first_messages": {
          "name": "first_messages",
          "type": "jsonb",
          "primaryKey": false,
          "notNull": true,
          "default": "'{\"content\":\"[クローズ]ボタンを押してこのスレッドをクローズできます!\",\"embeds\":[{\"description\":\"トラブルやBOTの不具合を報告してください!\"}],\"rows\":{\"version\":1,\"components\":[[{\"customId\":\"closeProcess:close:\",\"label\":\"クローズ\",\"emoji\":\"<:ai_chime:1465642091978690766>\",\"type\":\"button\",\"style\":4,\"buttonName\":\"クローズ\"}]]}}'::jsonb"
        },
        "created_at": {
          "name": "created_at",
          "type": "timestamp with time zone",
          "primaryKey": false,
          "notNull": true,
          "default": "now()"
        },
        "updated_at": {
          "name": "updated_at",
          "type": "timestamp with time zone",
          "primaryKey": false,
          "notNull": true,
          "default": "now()"
        }
      },
      "indexes": {
        "close_panel_panel_id_idx": {
          "name": "close_panel_panel_id_idx",
          "columns": [
            {
              "expression": "panel_id",
              "isExpression": false,
              "asc": true,
              "nulls": "last"
            }
          ],
          "isUnique": false,
          "concurrently": false,
          "method": "btree",
          "with": {}
        }
      },
      "foreignKeys": {},
      "compositePrimaryKeys": {},
      "uniqueConstraints": {},
      "policies": {},
      "checkConstraints": {},
      "isRLSEnabled": false
    },
    "public.ticket_info": {
      "name": "ticket_info",
      "schema": "",
      "columns": {
        "server_id": {
          "name": "server_id",
          "type": "varchar(19)",
          "primaryKey": false,
          "notNull": true
        },
        "channel_id": {
          "name": "channel_id",
          "type": "varchar(19)",
          "primaryKey": false,
          "notNull": true
        },
        "panel_id": {
          "name": "panel_id",
          "type": "varchar(19)",
          "primaryKey": true,
          "notNull": true
        },
        "send_close_panel_timing": {
          "name": "send_close_panel_timing",
          "type": "char(1)",
          "primaryKey": false,
          "notNull": true,
          "default": "'1'"
        },
        "main_panel": {
          "name": "main_panel",
          "type": "jsonb",
          "primaryKey": false,
          "notNull": true,
          "default": "'{\"content\":\"\",\"embeds\":[{\"description\":\"トラブルやBOTの不具合を報告してください!\"}],\"rows\":{\"version\":1,\"components\":[[{\"customId\":\"ticket_start\",\"label\":\"お問い合わせ作成\",\"emoji\":\"<:ai_open_letter:1465990917373694126>\",\"type\":\"button\",\"style\":3,\"buttonName\":\"お問い合わせ作成\"}]]}}'::jsonb"
        },
        "created_at": {
          "name": "created_at",
          "type": "timestamp with time zone",
          "primaryKey": false,
          "notNull": true,
          "default": "now()"
        },
        "updated_at": {
          "name": "updated_at",
          "type": "timestamp with time zone",
          "primaryKey": false,
          "notNull": true,
          "default": "now()"
        }
      },
      "indexes": {
        "ticket_info_panel_id_idx": {
          "name": "ticket_info_panel_id_idx",
          "columns": [
            {
              "expression": "panel_id",
              "isExpression": false,
              "asc": true,
              "nulls": "last"
            }
          ],
          "isUnique": false,
          "concurrently": false,
          "method": "btree",
          "with": {}
        },
        "ticket_info_panel_id_uniq": {
          "name": "ticket_info_panel_id_uniq",
          "columns": [
            {
              "expression": "panel_id",
              "isExpression": false,
              "asc": true,
              "nulls": "last"
            }
          ],
          "isUnique": true,
          "concurrently": false,
          "method": "btree",
          "with": {}
        }
      },
      "foreignKeys": {},
      "compositePrimaryKeys": {},
      "uniqueConstraints": {},
      "policies": {},
      "checkConstraints": {},
      "isRLSEnabled": false
    },
    "public.user_ticket": {
      "name": "user_ticket",
      "schema": "",
      "columns": {
        "ticket_id": {
          "name": "ticket_id",
          "type": "varchar(19)",
          "primaryKey": true,
          "notNull": true
        },
        "creator_id": {
          "name": "creator_id",
          "type": "varchar(19)",
          "primaryKey": false,
          "notNull": true
        },
        "created_at": {
          "name": "created_at",
          "type": "timestamp with time zone",
          "primaryKey": false,
          "notNull": true,
          "default": "now()"
        },
        "updated_at": {
          "name": "updated_at",
          "type": "timestamp with time zone",
          "primaryKey": false,
          "notNull": true,
          "default": "now()"
        }
      },
      "indexes": {
        "user_ticket_ticket_idx": {
          "name": "user_ticket_ticket_idx",
          "columns": [
            {
              "expression": "ticket_id",
              "isExpression": false,
              "asc": true,
              "nulls": "last"
            }
          ],
          "isUnique": false,
          "concurrently": false,
          "method": "btree",
          "with": {}
        }
      },
      "foreignKeys": {},
      "compositePrimaryKeys": {},
      "uniqueConstraints": {},
      "policies": {},
      "checkConstraints": {},
      "isRLSEnabled": false
    }
  },
  "enums": {},
  "schemas": {},
  "sequences": {},
  "roles": {},
  "policies": {},
  "views": {},
  "_meta": {
    "columns": {},
    "schemas": {},
    "tables": {}
  }
}